{
  "id": "org.weblate.cloudronapp",
  "version": "1.1.2",
  "title": "Weblate",
  "tagline": "Web-based continuous localization",
  "website": "https://weblate.org",
  "author": "Weblate developers",
  "contactEmail": "support@cloudron.io",
  "icon": "file://logo.png",
  "description": "file://DESCRIPTION.md",
  "postInstallMessage": "file://POSTINSTALL.md",
  "changelog": "file://CHANGELOG",
  "tags": ["translation", "localization", "transifex", "i18n", "l10n"],
  "mediaLinks": [
    "https://screenshots.cloudron.io/org.weblate.cloudronapp/weblate-01.png",
    "https://screenshots.cloudron.io/org.weblate.cloudronapp/weblate-02.png"
  ],
  "healthCheckPath": "/healthz/",
  "httpPort": 8000,
  "addons": {
    "localstorage": {},
    "ldap": {},
    "postgresql": {},
    "redis": {},
    "sendmail": {}
  },
  "optionalSso": true,
  "memoryLimit": 3758096384,
  "documentationUrl": "https://docs.cloudron.io/apps/weblate",
  "forumUrl": "https://forum.cloudron.io/category/106/weblate",
  "minBoxVersion": "5.3.0",
  "manifestVersion": 2
}
